warmup/DivisionCircuit.v
module Division(
    input         clock,
    input         start,
    input  [31:0] a,
    input  [31:0] b,
    output [31:0] q,
    output [31:0] r
);
    parameter n = 31;
	reg [31:0] r_curr;
    reg [31:0] rx;
    reg [31:0] qx;
    reg [31:0] i;
    reg enable;
    initial begin
		i = n;
        rx = 0;
        qx = 0;
        enable = 0;
    end

    always @(posedge start) enable = 1;

    always @(posedge clock && enable) begin
		if (!b || i == -1) begin
			enable = 0;
			// $finish; 
		end
        r_curr = rx << 1;
		r_curr = r_curr + a[i];
        if (r_curr < b) begin
            qx[i] = 0;
            rx = r_curr;
			//$display("q = 0");
        end else begin
            qx[i] = 1;
            rx = r_curr - b;
			//$display("q = 1");

        end
        i = i - 1;
    end
	assign q = qx;
    assign r = rx;

endmodule

warmup/MealyMachine.v
module MealyPattern(
	input        clock,
	input        i,
	output [1:0] o
);

/* q0 is the n-1 and q1 is n-2 input when i is the n-th input.
 o1 is the right bit of the output o and o0 is the left.*/
reg q0;
reg q1;
reg o0;
reg o1;
//different states of interest of the mealy machine
parameter 
	S11 = 2'b11,
	S00 = 2'b00,
	S10 = 2'b10;


always @(posedge clock) begin
	q0 <= i;
	q1 <= q0;
end

/*checks if q0q1 is 11 or 00 
  assigns o0 or o1 to 1 respectively*/
always @(i or q0)begin
	case ({q0,q1})
		S11: begin
			o0 = i ? 0 : 1;
			o1 = 0;
		end
		S00: begin
			o0 = 0;
			o1 = i ? 1 : 0;
		end
		S10: begin
			o1 = 0;
			o0 = 0;
		end
		default: begin
			o1 = 0;
			o0 = 0;
			//$display("here");
		end
	endcase	
end
assign o[1:0] = {o0,o1};
endmodule


module MealyPatternTestbench();

	reg[0:9]	str = 10'b1110011001;
	reg 		i;
	reg 		clk = 0;
	output[1:0] 	o;
	reg[0:31]	j;


	//instantiating 
	MealyPattern machine(.clock(clk), .i(i), .o(o));
	initial 
	begin
		$dumpfile("meal.vcd");
		$dumpvars;
	end

	//!! t2/t1 = 2 has to be true. doesn't work otherwise ¯\_(ツ)_/¯
	always #1 clk = !clk; //t1
	
	initial begin
	for (j = 0; j < 10; j=j+1) begin
		i = str[j];
		#2 //t2 - wait for the combi. circuit
		$display ("input: %b, output: %2b",i,o);
	end


	#1 $finish;
	end

endmodule

warmup/SanitizerWarmup.v
module SanitizerWarmup();

	MealyPatternTestbench tb();

	wire clock, inp;
	wire [1:0] outp;
	MealyPattern mp(.clock(clock), .i(inp), .o(outp));

	wire        start;
	wire [31:0] a;
	wire [31:0] b;
	wire [31:0] q;
	wire [31:0] r;
	Division divs(
		.clock(clock),
		.start(start),
		.a(a),
		.b(b),
		.q(q),
		.r(r)
	);

	initial
		begin
			// Generate a waveform output
			$dumpfile("simres.vcd");
			$dumpvars(0, tb.machine);
			$dumpvars(0, tb.machine.i);
			$dumpvars(0, tb.machine.o);
			$dumpvars(0, tb.machine.clock);
		end

endmodule

warmup/meal.vcd
$date
	Mon Jun 13 17:47:43 2022
$end
$version
	Icarus Verilog
$end
$timescale
	1s
$end
$scope module SanitizerWarmup $end
$var wire 32 ! a [31:0] $end
$var wire 32 " b [31:0] $end
$var wire 1 # clock $end
$var wire 1 $ inp $end
$var wire 1 % start $end
$var wire 32 & r [31:0] $end
$var wire 32 ' q [31:0] $end
$var wire 2 ( outp [1:0] $end
$scope module divs $end
$var wire 32 ) a [31:0] $end
$var wire 32 * b [31:0] $end
$var wire 1 # clock $end
$var wire 32 + q [31:0] $end
$var wire 32 , r [31:0] $end
$var wire 1 % start $end
$var reg 1 - enable $end
$var reg 32 . i [31:0] $end
$var reg 32 / qx [31:0] $end
$var reg 32 0 r_curr [31:0] $end
$var reg 32 1 rx [31:0] $end
$upscope $end
$scope module mp $end
$var wire 1 # clock $end
$var wire 1 $ i $end
$var wire 2 2 o [1:0] $end
$var reg 1 3 o0 $end
$var reg 1 4 o1 $end
$var reg 1 5 q0 $end
$var reg 1 6 q1 $end
$upscope $end
$scope module tb $end
$var wire 2 7 o [1:0] $end
$var reg 1 8 clk $end
$var reg 1 9 i $end
$var reg 32 : j [0:31] $end
$var reg 10 ; str [0:9] $end
$scope module machine $end
$var wire 1 8 clock $end
$var wire 1 9 i $end
$var wire 2 < o [1:0] $end
$var reg 1 = o0 $end
$var reg 1 > o1 $end
$var reg 1 ? q0 $end
$var reg 1 @ q1 $end
$upscope $end
$upscope $end
$upscope $end
$scope module SanitizerWarmup $end
$scope module tb $end
$scope module machine $end
$upscope $end
$upscope $end
$upscope $end
$enddefinitions $end
#0
$dumpvars
x@
x?
0>
0=
b0 <
b1110011001 ;
b0 :
19
08
b0 7
x6
x5
04
03
b0 2
b0 1
bx 0
b0 /
b11111 .
0-
b0 ,
b0 +
bz *
bz )
b0 (
b0 '
b0 &
z%
z$
z#
bz "
bz !
$end
#1
1?
18
#2
08
b1 :
#3
1@
18
#4
08
b10 :
#5
18
#6
b10 7
b10 <
1=
08
09
b11 :
#7
b0 7
b0 <
0=
0?
18
#8
08
b100 :
#9
0@
18
#10
b1 7
b1 <
1>
08
19
b101 :
#11
b0 7
b0 <
0>
1?
18
#12
08
b110 :
#13
1@
18
#14
b10 7
b10 <
1=
08
09
b111 :
#15
b0 7
b0 <
0=
0?
18
#16
08
b1000 :
#17
0@
18
#18
b1 7
b1 <
1>
08
19
b1001 :
#19
b0 7
b0 <
0>
1?
18
#20
08
b1010 :
#21
1@
18
